[{"batsman":"Rassie van der Dussen","runs":"67","balls":"64","four":"2","six":"3","strikeRate":"104.68"},{"batsman":"Rassie van der Dussen","runs":"22","balls":"37","four":"1","six":"0","strikeRate":"59.45"},{"batsman":"Rassie van der Dussen","runs":"41","balls":"38","four":"2","six":"1","strikeRate":"107.89"},{"batsman":"Rassie van der Dussen","runs":"50","balls":"61","four":"4","six":"1","strikeRate":"81.96"},{"batsman":"Rassie van der Dussen","runs":"36","balls":"47","four":"1","six":"1","strikeRate":"76.59"},{"batsman":"Rassie van der Dussen","runs":"95","balls":"97","four":"4","six":"4","strikeRate":"97.93"}]